{"sections":{"main":{"type":"main-page","settings":{"padding_top":28,"padding_bottom":0}},"rich_text_Vxg6EU":{"type":"rich-text","blocks":{"heading_p3VUFm":{"type":"heading","settings":{"heading":"","heading_size":"h1"}},"text_cxXnPn":{"type":"text","settings":{"text":""}},"button_m8jyqV":{"type":"button","settings":{"button_label":"ENTER THE ARMORY","button_link":"shopify:\/\/collections\/the-armory","button_style_secondary":true,"button_label_2":"","button_link_2":"","button_style_secondary_2":false}}},"block_order":["heading_p3VUFm","text_cxXnPn","button_m8jyqV"],"name":"t:sections.rich-text.presets.name","settings":{"desktop_content_position":"center","content_alignment":"left","color_scheme":"","full_width":true,"padding_top":0,"padding_bottom":28}}},"order":["main","rich_text_Vxg6EU"]}